WSKrystian/WebScrapingKrystian.py
WSKrystian/__init__.py
WSKrystian-6.0.1.dist-info/LICENSE
WSKrystian-6.0.1.dist-info/METADATA
WSKrystian-6.0.1.dist-info/WHEEL
WSKrystian-6.0.1.dist-info/top_level.txt
WSKrystian-6.0.1.dist-info/RECORD
