Metadata-Version: 2.1
Name: WSKrystian
Version: 6.0.1
Summary: Web scraping simplified
Home-page: UNKNOWN
Author: Krystian Pielat
Author-email: krystian.pielat@onet.pl
License: UNKNOWN
Keywords: selenium,web scraping
Platform: UNKNOWN
Classifier: Development Status :: 1 - Planning
Classifier: Intended Audience :: Developers
Classifier: Programming Language :: Python :: 3
Classifier: Operating System :: Unix
Classifier: Operating System :: MacOS :: MacOS X
Classifier: Operating System :: Microsoft :: Windows
License-File: LICENSE
Requires-Dist: selenium
Requires-Dist: bs4
Requires-Dist: requests
